{
    "os": "Linux-5.10.0-26-amd64-x86_64-with-glibc2.31",
    "python": "3.9.2",
    "heartbeatAt": "2024-03-18T15:04:42.771527",
    "startedAt": "2024-03-18T15:04:42.269110",
    "docker": null,
    "cuda": null,
    "args": [],
    "state": "running",
    "program": "/home/p.le-tolguenec/Documents/contrastive_exploration/src/baselines/ngu.py",
    "codePath": "src/baselines/ngu.py",
    "git": {
        "remote": "https://github.com/Paul-antoineLeTolguenec/contrastive_exploration.git",
        "commit": "1766be7846b54931c70ff8a89d67c36c50e2568e"
    },
    "email": "paul-antoine.le_tolguenec@ensta-bretagne.org",
    "root": "/home/p.le-tolguenec/Documents/contrastive_exploration",
    "host": "bubo",
    "username": "p.le-tolguenec",
    "executable": "/home/p.le-tolguenec/torch-pa/bin/python3",
    "cpu_count": 8,
    "cpu_count_logical": 16,
    "cpu_freq": {
        "current": 4761.317,
        "min": 800.0,
        "max": 5000.0
    },
    "cpu_freq_per_core": [
        {
            "current": 4798.657,
            "min": 800.0,
            "max": 5000.0
        },
        {
            "current": 4743.172,
            "min": 800.0,
            "max": 5000.0
        },
        {
            "current": 4794.937,
            "min": 800.0,
            "max": 5000.0
        },
        {
            "current": 4739.551,
            "min": 800.0,
            "max": 5000.0
        },
        {
            "current": 4737.679,
            "min": 800.0,
            "max": 5000.0
        },
        {
            "current": 4799.031,
            "min": 800.0,
            "max": 5000.0
        },
        {
            "current": 4790.514,
            "min": 800.0,
            "max": 5000.0
        },
        {
            "current": 4718.246,
            "min": 800.0,
            "max": 5000.0
        },
        {
            "current": 4773.481,
            "min": 800.0,
            "max": 5000.0
        },
        {
            "current": 4730.58,
            "min": 800.0,
            "max": 5000.0
        },
        {
            "current": 4703.097,
            "min": 800.0,
            "max": 5000.0
        },
        {
            "current": 4781.709,
            "min": 800.0,
            "max": 5000.0
        },
        {
            "current": 4790.52,
            "min": 800.0,
            "max": 5000.0
        },
        {
            "current": 4737.709,
            "min": 800.0,
            "max": 5000.0
        },
        {
            "current": 4798.434,
            "min": 800.0,
            "max": 5000.0
        },
        {
            "current": 4743.755,
            "min": 800.0,
            "max": 5000.0
        }
    ],
    "disk": {
        "total": 467.8895797729492,
        "used": 11.540786743164062
    },
    "gpu": "NVIDIA GeForce RTX 2070",
    "gpu_count": 1,
    "gpu_devices": [
        {
            "name": "NVIDIA GeForce RTX 2070",
            "memory_total": 8367570944
        }
    ],
    "memory": {
        "total": 62.60514450073242
    }
}
